exec_client.py
exec_server.py
exec_siren.py
blocks/__init__.py
blocks/common_details.py
blocks/data/icons/cross.png
blocks/data/icons/down_right.png
blocks/data/icons/learn_act.png
blocks/data/icons/learn_dis.png
blocks/data/icons/savefig.png
blocks/data/icons/siren_dmg_icon.png
blocks/data/icons/siren_file_icon.png
blocks/data/icons/siren_icon.ico
blocks/data/icons/siren_icon.png
blocks/data/icons/siren_icon32x32.png
blocks/data/icons/split.png
blocks/data/icons/stamp.png
blocks/data/icons/test_act.png
blocks/data/icons/test_dis.png
blocks/data/icons/unsplit.png
blocks/data/icons/up_right.png
blocks/data/icons/usiren_icon.ico
blocks/data/licenses/LICENSE
blocks/data/licenses/LICENSE.txt
blocks/data/licenses/LICENSE_basemap
blocks/data/licenses/LICENSE_grako
blocks/data/licenses/LICENSE_matplotlib
blocks/data/licenses/LICENSE_python
blocks/data/licenses/LICENSE_wx
blocks/interface/DataWrapper.py
blocks/interface/__init__.py
blocks/interface/classConnectionDialog.py
blocks/interface/classContentTable.py
blocks/interface/classExtensionsDialog.py
blocks/interface/classFoldsDialog.py
blocks/interface/classGridTable.py
blocks/interface/classPreferencesDialog.py
blocks/interface/classSiren.py
blocks/interface/miscDialogs.py
blocks/interface/ui_confdef.xml
blocks/mine/__init__.py
blocks/mine/actions_rdefs_basic.txt
blocks/mine/classCandidates.py
blocks/mine/classCharbon.py
blocks/mine/classCharbonGMiss.py
blocks/mine/classCharbonGStd.py
blocks/mine/classCharbonGreedy.py
blocks/mine/classCharbonTAlt.py
blocks/mine/classCharbonTLayer.py
blocks/mine/classCharbonXFIM.py
blocks/mine/classCol.py
blocks/mine/classConstraints.py
blocks/mine/classContent.py
blocks/mine/classDTreeTools.py
blocks/mine/classData.py
blocks/mine/classDataExtension.py
blocks/mine/classMiner.py
blocks/mine/classPackage.py
blocks/mine/classPreferencesManager.py
blocks/mine/classProps.py
blocks/mine/classQuery.py
blocks/mine/classRedescription.py
blocks/mine/classRndFactory.py
blocks/mine/classSParts.py
python_siren-6.0.8.dist-info/LICENSE
python_siren-6.0.8.dist-info/METADATA
python_siren-6.0.8.dist-info/WHEEL
python_siren-6.0.8.dist-info/entry_points.txt
python_siren-6.0.8.dist-info/top_level.txt
python_siren-6.0.8.dist-info/RECORD
