Metadata-Version: 2.1
Name: python-siren
Version: 6.0.8
Summary: Interactive Redescription Mining
Home-page: http://cs.uef.fi/siren/
Author: Esther Galbrun and Pauli Miettinen
Author-email: esther.galbrun@inria.fr
License: Apache_2.0
Platform: UNKNOWN
Classifier: Development Status :: 4 - Beta
Classifier: License :: OSI Approved :: Apache Software License
Classifier: Programming Language :: Python :: 3
Classifier: Operating System :: OS Independent
Classifier: Topic :: Scientific/Engineering
Requires-Python: >=3
Requires-Dist: cartopy (>=0.14)
Requires-Dist: matplotlib (>=2.1.0)
Requires-Dist: numpy (>=1.13.0)
Requires-Dist: python-dateutil (>=2.7.3)
Requires-Dist: scikit-learn (>=0.19.0)
Requires-Dist: scipy (>=0.19.0)
Requires-Dist: shapely (>=1.7.0)
Requires-Dist: wxPython (>=4.0.0)
